base_configurations/__init__.py
base_configurations/base_configurations.py
base_configurations/cache_in_db.py
base_configurations/ckeditor.py
base_configurations/djmoney.py
base_configurations/easy_thumbnail.py
base_configurations/installed_apps.py
base_configurations/middleware.py
base_configurations/urlpatterns.py
base_navbar/__init__.py
base_navbar/admin.py
base_navbar/apps.py
base_navbar/models.py
base_navbar/tests.py
base_navbar/urls.py
base_navbar/views.py
base_navbar/management/__init__.py
base_navbar/management/commands/__init__.py
base_navbar/migrations/0001_initial.py
base_navbar/migrations/__init__.py
base_navbar/service/__init__.py
base_navbar/service/get_navbar.py
base_navbar/style/css_base.css
base_navbar/style/css_items.txt
base_navbar/templates/base_navbar/base_navbar.html
base_navbar/templates/base_navbar/test.html
base_navbar/templates/base_navbar/bs5/navbar.html
base_navbar/templates/base_navbar/bs5/navbar_items.html
base_navbar/templates/base_navbar/offcanvas/body.html
base_navbar/templates/base_navbar/offcanvas/body_text.html
base_navbar/templates/base_navbar/offcanvas/call.html
base_navbar/templates/base_navbar/offcanvas/family_item.html
base_navbar/templates/base_navbar/offcanvas/full.html
base_navbar/templates/base_navbar/offcanvas/header.html
base_navbar/templates/base_navbar/offcanvas/lonely_item.html
base_navbar/templatetags/__init__.py
base_navbar/templatetags/base_navbar.py
base_template/__init__.py
base_template/admin.py
base_template/apps.py
base_template/models.py
base_template/tests.py
base_template/urls.py
base_template/views.py
base_template/management/__init__.py
base_template/management/commands/__init__.py
base_template/management/commands/bootstrap4_init.py
base_template/management/commands/bootstrap5_init.py
base_template/migrations/0001_initial.py
base_template/migrations/__init__.py
base_template/service/__init__.py
base_template/service/get_base_template_cache_time.py
base_template/service/get_body_scripts.py
easy_django-0.0.2.dist-info/LICENSE
easy_django-0.0.2.dist-info/METADATA
easy_django-0.0.2.dist-info/WHEEL
easy_django-0.0.2.dist-info/top_level.txt
easy_django-0.0.2.dist-info/RECORD
