Metadata-Version: 2.1
Name: easy-django
Version: 0.0.2
Summary: easy django
Home-page: https://github.com/gergerov/easy_django
Author: gergerov
Author-email: gergerov94@gmail.com
License: Commercial
Platform: UNKNOWN
Classifier: Environment :: Web Environment
Classifier: Framework :: Django :: 3.2
Classifier: Intended Audience :: Developers
Classifier: License :: OSI Approved :: MIT License
Classifier: Operating System :: OS Independent
Classifier: Programming Language :: Python :: 3.8
Classifier: Topic :: Internet :: WWW/HTTP
Requires-Python: >=3.8
Requires-Dist: Django (>=3.2)
Requires-Dist: django-rest-framework
Requires-Dist: django-ckeditor
Requires-Dist: easy-thumbnails
Requires-Dist: django-money
